{"__symbolic":"module","version":4,"metadata":{"DynamicKendoAutoCompleteComponent":{"__symbolic":"class","extends":{"__symbolic":"reference","name":"DynamicKendoTemplateableFormControlComponent"},"decorators":[{"__symbolic":"call","expression":{"__symbolic":"reference","module":"@angular/core","name":"Component","line":14,"character":1},"arguments":[{"selector":"dynamic-kendo-autocomplete","changeDetection":{"__symbolic":"select","expression":{"__symbolic":"reference","module":"@angular/core","name":"ChangeDetectionStrategy","line":17,"character":21},"member":"OnPush"},"template":"<ng-container [formGroup]=\"group\">\r\n\r\n    <kendo-autocomplete #kendoAutoComplete\r\n                        [data]=\"model.list\"\r\n                        [dynamicId]=\"bindId && model.id\"\r\n                        [formControlName]=\"model.id\"\r\n                        [ngClass]=\"[getClass('element', 'control'), getClass('grid', 'control')]\"\r\n                        [placeholder]=\"model.placeholder\"\r\n                        [popupSettings]=\"model.getAdditional('popupSettings', {})\"\r\n                        [suggest]=\"model.getAdditional('suggest', false)\"\r\n                        [tabIndex]=\"model.tabIndex\"\r\n                        (blur)=\"onBlur($event)\"\r\n                        (close)=\"onCustomEvent($event, 'close')\"\r\n                        (filterChange)=\"onCustomEvent($event, 'filterChange')\"\r\n                        (focus)=\"onFocus($event)\"\r\n                        (open)=\"onCustomEvent($event, 'open')\"\r\n                        (valueChange)=\"onChange($event)\"></kendo-autocomplete>\r\n\r\n</ng-container>"}]}],"members":{"bindId":[{"__symbolic":"property","decorators":[{"__symbolic":"call","expression":{"__symbolic":"reference","module":"@angular/core","name":"Input","line":23,"character":5}}]}],"group":[{"__symbolic":"property","decorators":[{"__symbolic":"call","expression":{"__symbolic":"reference","module":"@angular/core","name":"Input","line":24,"character":5}}]}],"layout":[{"__symbolic":"property","decorators":[{"__symbolic":"call","expression":{"__symbolic":"reference","module":"@angular/core","name":"Input","line":25,"character":5}}]}],"model":[{"__symbolic":"property","decorators":[{"__symbolic":"call","expression":{"__symbolic":"reference","module":"@angular/core","name":"Input","line":26,"character":5}}]}],"templates":[{"__symbolic":"property","decorators":[{"__symbolic":"call","expression":{"__symbolic":"reference","module":"@angular/core","name":"Input","line":27,"character":5}}]}],"blur":[{"__symbolic":"property","decorators":[{"__symbolic":"call","expression":{"__symbolic":"reference","module":"@angular/core","name":"Output","line":29,"character":5}}]}],"change":[{"__symbolic":"property","decorators":[{"__symbolic":"call","expression":{"__symbolic":"reference","module":"@angular/core","name":"Output","line":30,"character":5}}]}],"customEvent":[{"__symbolic":"property","decorators":[{"__symbolic":"call","expression":{"__symbolic":"reference","module":"@angular/core","name":"Output","line":31,"character":5}}]}],"focus":[{"__symbolic":"property","decorators":[{"__symbolic":"call","expression":{"__symbolic":"reference","module":"@angular/core","name":"Output","line":32,"character":5}}]}],"kendoAutoComplete":[{"__symbolic":"property","decorators":[{"__symbolic":"call","expression":{"__symbolic":"reference","module":"@angular/core","name":"ViewChild","line":34,"character":5},"arguments":["kendoAutoComplete"]}]}],"__ctor__":[{"__symbolic":"constructor","parameters":[{"__symbolic":"reference","module":"@ng-dynamic-forms/core","name":"DynamicFormLayoutService","line":36,"character":41},{"__symbolic":"reference","module":"@ng-dynamic-forms/core","name":"DynamicFormValidationService","line":37,"character":45}]}]}},"DynamicKendoCalendarComponent":{"__symbolic":"class","extends":{"__symbolic":"reference","name":"DynamicKendoTemplateableFormControlComponent"},"decorators":[{"__symbolic":"call","expression":{"__symbolic":"reference","module":"@angular/core","name":"Component","line":14,"character":1},"arguments":[{"selector":"dynamic-kendo-calendar","changeDetection":{"__symbolic":"select","expression":{"__symbolic":"reference","module":"@angular/core","name":"ChangeDetectionStrategy","line":17,"character":21},"member":"OnPush"},"template":"<ng-container [formGroup]=\"group\">\r\n\r\n    <kendo-calendar #kendoCalendar\r\n                    [activeView]=\"model.getAdditional('activeView', 'month')\"\r\n                    [bottomView]=\"model.getAdditional('bottomView', 'month')\"\r\n                    [dynamicId]=\"bindId && model.id\"\r\n                    [focusedDate]=\"model.focusedDate\"\r\n                    [formControlName]=\"model.id\"\r\n                    [max]=\"model.max\"\r\n                    [min]=\"model.min\"\r\n                    [navigation]=\"model.getAdditional('navigation', true)\"\r\n                    [ngClass]=\"[getClass('element', 'control'), getClass('grid', 'control')]\"\r\n                    [rangeValidation]=\"model.getAdditional('rangeValidation', true)\"\r\n                    [tabindex]=\"model.tabIndex\"\r\n                    [topView]=\"model.getAdditional('topView', 'century')\"\r\n                    [weekNumber]=\"model.getAdditional('weekNumber', false)\"\r\n                    (activeViewChange)=\"onCustomEvent($event, 'activeViewChange')\"\r\n                    (activeViewDateChange)=\"onCustomEvent($event, 'activeViewDateChange')\"\r\n                    (valueChange)=\"onChange($event)\"></kendo-calendar>\r\n\r\n</ng-container>"}]}],"members":{"bindId":[{"__symbolic":"property","decorators":[{"__symbolic":"call","expression":{"__symbolic":"reference","module":"@angular/core","name":"Input","line":23,"character":5}}]}],"group":[{"__symbolic":"property","decorators":[{"__symbolic":"call","expression":{"__symbolic":"reference","module":"@angular/core","name":"Input","line":24,"character":5}}]}],"layout":[{"__symbolic":"property","decorators":[{"__symbolic":"call","expression":{"__symbolic":"reference","module":"@angular/core","name":"Input","line":25,"character":5}}]}],"model":[{"__symbolic":"property","decorators":[{"__symbolic":"call","expression":{"__symbolic":"reference","module":"@angular/core","name":"Input","line":26,"character":5}}]}],"templates":[{"__symbolic":"property","decorators":[{"__symbolic":"call","expression":{"__symbolic":"reference","module":"@angular/core","name":"Input","line":27,"character":5}}]}],"blur":[{"__symbolic":"property","decorators":[{"__symbolic":"call","expression":{"__symbolic":"reference","module":"@angular/core","name":"Output","line":29,"character":5}}]}],"change":[{"__symbolic":"property","decorators":[{"__symbolic":"call","expression":{"__symbolic":"reference","module":"@angular/core","name":"Output","line":30,"character":5}}]}],"customEvent":[{"__symbolic":"property","decorators":[{"__symbolic":"call","expression":{"__symbolic":"reference","module":"@angular/core","name":"Output","line":31,"character":5}}]}],"focus":[{"__symbolic":"property","decorators":[{"__symbolic":"call","expression":{"__symbolic":"reference","module":"@angular/core","name":"Output","line":32,"character":5}}]}],"kendoCalendar":[{"__symbolic":"property","decorators":[{"__symbolic":"call","expression":{"__symbolic":"reference","module":"@angular/core","name":"ViewChild","line":34,"character":5},"arguments":["kendoCalendar"]}]}],"__ctor__":[{"__symbolic":"constructor","parameters":[{"__symbolic":"reference","module":"@ng-dynamic-forms/core","name":"DynamicFormLayoutService","line":36,"character":41},{"__symbolic":"reference","module":"@ng-dynamic-forms/core","name":"DynamicFormValidationService","line":37,"character":45}]}]}},"DynamicKendoCheckboxComponent":{"__symbolic":"class","extends":{"__symbolic":"reference","module":"@ng-dynamic-forms/core","name":"DynamicFormControlComponent","line":15,"character":51},"decorators":[{"__symbolic":"call","expression":{"__symbolic":"reference","module":"@angular/core","name":"Component","line":10,"character":1},"arguments":[{"selector":"dynamic-kendo-checkbox","changeDetection":{"__symbolic":"select","expression":{"__symbolic":"reference","module":"@angular/core","name":"ChangeDetectionStrategy","line":13,"character":21},"member":"OnPush"},"template":"<label [formGroup]=\"group\" class=\"k-form-field\" [ngClass]=\"getClass('grid', 'control')\">\r\n\r\n    <input type=\"checkbox\" class=\"k-checkbox\"\r\n           [checked]=\"model.checked\"\r\n           [dynamicId]=\"bindId && model.id\"\r\n           [formControlName]=\"model.id\"\r\n           [indeterminate]=\"model.indeterminate\"\r\n           [name]=\"model.name\"\r\n           [ngClass]=\"getClass('element', 'control')\"\r\n           [required]=\"model.required\"\r\n           [tabindex]=\"model.tabIndex\"\r\n           [value]=\"model.value\"\r\n           (blur)=\"onBlur($event)\"\r\n           (change)=\"onChange($event)\"\r\n           (focus)=\"onFocus($event)\"/>\r\n\r\n    <label class=\"k-checkbox-label\" [for]=\"model.id\" [innerHTML]=\"model.label\"></label>\r\n\r\n</label>"}]}],"members":{"bindId":[{"__symbolic":"property","decorators":[{"__symbolic":"call","expression":{"__symbolic":"reference","module":"@angular/core","name":"Input","line":17,"character":5}}]}],"group":[{"__symbolic":"property","decorators":[{"__symbolic":"call","expression":{"__symbolic":"reference","module":"@angular/core","name":"Input","line":18,"character":5}}]}],"layout":[{"__symbolic":"property","decorators":[{"__symbolic":"call","expression":{"__symbolic":"reference","module":"@angular/core","name":"Input","line":19,"character":5}}]}],"model":[{"__symbolic":"property","decorators":[{"__symbolic":"call","expression":{"__symbolic":"reference","module":"@angular/core","name":"Input","line":20,"character":5}}]}],"blur":[{"__symbolic":"property","decorators":[{"__symbolic":"call","expression":{"__symbolic":"reference","module":"@angular/core","name":"Output","line":22,"character":5}}]}],"change":[{"__symbolic":"property","decorators":[{"__symbolic":"call","expression":{"__symbolic":"reference","module":"@angular/core","name":"Output","line":23,"character":5}}]}],"focus":[{"__symbolic":"property","decorators":[{"__symbolic":"call","expression":{"__symbolic":"reference","module":"@angular/core","name":"Output","line":24,"character":5}}]}],"__ctor__":[{"__symbolic":"constructor","parameters":[{"__symbolic":"reference","module":"@ng-dynamic-forms/core","name":"DynamicFormLayoutService","line":26,"character":41},{"__symbolic":"reference","module":"@ng-dynamic-forms/core","name":"DynamicFormValidationService","line":27,"character":45}]}]}},"DynamicKendoCheckboxGroupComponent":{"__symbolic":"class","extends":{"__symbolic":"reference","module":"@ng-dynamic-forms/core","name":"DynamicFormControlComponent","line":14,"character":56},"decorators":[{"__symbolic":"call","expression":{"__symbolic":"reference","module":"@angular/core","name":"Component","line":10,"character":1},"arguments":[{"selector":"dynamic-kendo-checkbox-group","template":"<ng-container [formGroup]=\"group\">\r\n\r\n    <fieldset class=\"k-form-field\"\r\n              [dynamicId]=\"bindId && model.id\"\r\n              [formGroupName]=\"model.id\"\r\n              [name]=\"model.name\"\r\n              [ngClass]=\"[getClass('element', 'control'), getClass('grid', 'control')]\">\r\n\r\n        <legend *ngIf=\"model.legend\" [innerHTML]=\"model.legend\"></legend>\r\n\r\n        <ng-container *ngFor=\"let checkboxModel of model.group\">\r\n\r\n            <input type=\"checkbox\" class=\"k-checkbox\"\r\n                   [checked]=\"checkboxModel.checked\"\r\n                   [dynamicId]=\"bindId && checkboxModel.id\"\r\n                   [formControlName]=\"checkboxModel.id\"\r\n                   [indeterminate]=\"checkboxModel.indeterminate\"\r\n                   [name]=\"checkboxModel.name\"\r\n                   [ngClass]=\"getClass('element', 'control', checkboxModel)\"\r\n                   [required]=\"checkboxModel.required\"\r\n                   [tabindex]=\"checkboxModel.tabIndex\"\r\n                   [value]=\"checkboxModel.value\"\r\n                   (blur)=\"onBlur($event)\"\r\n                   (change)=\"onEmbeddedCheckboxChange($event, model)\"\r\n                   (focus)=\"onFocus($event)\"/>\r\n\r\n            <label class=\"k-checkbox-label\" [for]=\"checkboxModel.id\" [innerHTML]=\"checkboxModel.label\"></label>\r\n\r\n        </ng-container>\r\n\r\n    </fieldset>\r\n\r\n</ng-container>"}]}],"members":{"bindId":[{"__symbolic":"property","decorators":[{"__symbolic":"call","expression":{"__symbolic":"reference","module":"@angular/core","name":"Input","line":16,"character":5}}]}],"group":[{"__symbolic":"property","decorators":[{"__symbolic":"call","expression":{"__symbolic":"reference","module":"@angular/core","name":"Input","line":17,"character":5}}]}],"layout":[{"__symbolic":"property","decorators":[{"__symbolic":"call","expression":{"__symbolic":"reference","module":"@angular/core","name":"Input","line":18,"character":5}}]}],"model":[{"__symbolic":"property","decorators":[{"__symbolic":"call","expression":{"__symbolic":"reference","module":"@angular/core","name":"Input","line":19,"character":5}}]}],"blur":[{"__symbolic":"property","decorators":[{"__symbolic":"call","expression":{"__symbolic":"reference","module":"@angular/core","name":"Output","line":21,"character":5}}]}],"change":[{"__symbolic":"property","decorators":[{"__symbolic":"call","expression":{"__symbolic":"reference","module":"@angular/core","name":"Output","line":22,"character":5}}]}],"focus":[{"__symbolic":"property","decorators":[{"__symbolic":"call","expression":{"__symbolic":"reference","module":"@angular/core","name":"Output","line":23,"character":5}}]}],"__ctor__":[{"__symbolic":"constructor","parameters":[{"__symbolic":"reference","module":"@ng-dynamic-forms/core","name":"DynamicFormLayoutService","line":25,"character":41},{"__symbolic":"reference","module":"@ng-dynamic-forms/core","name":"DynamicFormValidationService","line":26,"character":45}]}]}},"DynamicKendoDateInputComponent":{"__symbolic":"class","extends":{"__symbolic":"reference","module":"@ng-dynamic-forms/core","name":"DynamicFormControlComponent","line":16,"character":52},"decorators":[{"__symbolic":"call","expression":{"__symbolic":"reference","module":"@angular/core","name":"Component","line":11,"character":1},"arguments":[{"selector":"dynamic-kendo-dateinput","changeDetection":{"__symbolic":"select","expression":{"__symbolic":"reference","module":"@angular/core","name":"ChangeDetectionStrategy","line":14,"character":21},"member":"OnPush"},"template":"<ng-container [formGroup]=\"group\">\r\n\r\n    <kendo-dateinput #kendoDateInput\r\n                     [dynamicId]=\"bindId && model.id\"\r\n                     [format]=\"model.getAdditional('format', 'd')\"\r\n                     [formatPlaceholder]=\"model.getAdditional('formatPlaceholder', 'wide')\"\r\n                     [formControlName]=\"model.id\"\r\n                     [max]=\"model.max\"\r\n                     [min]=\"model.min\"\r\n                     [ngClass]=\"[getClass('element', 'control'), getClass('grid', 'control')]\"\r\n                     [rangeValidation]=\"model.getAdditional('rangeValidation', true)\"\r\n                     [spinners]=\"model.getAdditional('spinners', true)\"\r\n                     [tabindex]=\"model.tabIndex\"\r\n                     (blur)=\"onBlur($event)\"\r\n                     (focus)=\"onFocus($event)\"\r\n                     (valueChange)=\"onChange($event)\"></kendo-dateinput>\r\n\r\n</ng-container>"}]}],"members":{"bindId":[{"__symbolic":"property","decorators":[{"__symbolic":"call","expression":{"__symbolic":"reference","module":"@angular/core","name":"Input","line":18,"character":5}}]}],"group":[{"__symbolic":"property","decorators":[{"__symbolic":"call","expression":{"__symbolic":"reference","module":"@angular/core","name":"Input","line":19,"character":5}}]}],"layout":[{"__symbolic":"property","decorators":[{"__symbolic":"call","expression":{"__symbolic":"reference","module":"@angular/core","name":"Input","line":20,"character":5}}]}],"model":[{"__symbolic":"property","decorators":[{"__symbolic":"call","expression":{"__symbolic":"reference","module":"@angular/core","name":"Input","line":21,"character":5}}]}],"blur":[{"__symbolic":"property","decorators":[{"__symbolic":"call","expression":{"__symbolic":"reference","module":"@angular/core","name":"Output","line":23,"character":5}}]}],"change":[{"__symbolic":"property","decorators":[{"__symbolic":"call","expression":{"__symbolic":"reference","module":"@angular/core","name":"Output","line":24,"character":5}}]}],"focus":[{"__symbolic":"property","decorators":[{"__symbolic":"call","expression":{"__symbolic":"reference","module":"@angular/core","name":"Output","line":25,"character":5}}]}],"kendoDateInput":[{"__symbolic":"property","decorators":[{"__symbolic":"call","expression":{"__symbolic":"reference","module":"@angular/core","name":"ViewChild","line":27,"character":5},"arguments":["kendoDateInput"]}]}],"__ctor__":[{"__symbolic":"constructor","parameters":[{"__symbolic":"reference","module":"@ng-dynamic-forms/core","name":"DynamicFormLayoutService","line":29,"character":41},{"__symbolic":"reference","module":"@ng-dynamic-forms/core","name":"DynamicFormValidationService","line":30,"character":45}]}]}},"DynamicKendoDatePickerComponent":{"__symbolic":"class","extends":{"__symbolic":"reference","module":"@ng-dynamic-forms/core","name":"DynamicFormControlComponent","line":17,"character":53},"decorators":[{"__symbolic":"call","expression":{"__symbolic":"reference","module":"@angular/core","name":"Component","line":12,"character":1},"arguments":[{"selector":"dynamic-kendo-datepicker","changeDetection":{"__symbolic":"select","expression":{"__symbolic":"reference","module":"@angular/core","name":"ChangeDetectionStrategy","line":15,"character":21},"member":"OnPush"},"template":"<ng-container [formGroup]=\"group\">\r\n\r\n    <kendo-datepicker #kendoDatePicker\r\n                      [activeView]=\"model.getAdditional('activeView', 'month')\"\r\n                      [bottomView]=\"model.getAdditional('bottomView', 'month')\"\r\n                      [dynamicId]=\"bindId && model.id\"\r\n                      [focusedDate]=\"model.focusedDate\"\r\n                      [format]=\"model.format || 'd'\"\r\n                      [formControlName]=\"model.id\"\r\n                      [max]=\"model.max\"\r\n                      [min]=\"model.min\"\r\n                      [navigation]=\"model.getAdditional('navigation', true)\"\r\n                      [ngClass]=\"[getClass('element', 'control'), getClass('grid', 'control')]\"\r\n                      [popupSettings]=\"model.getAdditional('popupSettings', {})\"\r\n                      [rangeValidation]=\"model.getAdditional('rangeValidation', true)\"\r\n                      [tabindex]=\"model.tabIndex\"\r\n                      [topView]=\"model.getAdditional('topView', 'century')\"\r\n                      [weekNumber]=\"model.getAdditional('weekNumber', false)\"\r\n                      (blur)=\"onBlur($event)\"\r\n                      (close)=\"onCustomEvent($event, 'close')\"\r\n                      (focus)=\"onFocus($event)\"\r\n                      (open)=\"onCustomEvent($event, 'open')\"\r\n                      (valueChange)=\"onChange($event)\"></kendo-datepicker>\r\n\r\n</ng-container>"}]}],"members":{"bindId":[{"__symbolic":"property","decorators":[{"__symbolic":"call","expression":{"__symbolic":"reference","module":"@angular/core","name":"Input","line":19,"character":5}}]}],"group":[{"__symbolic":"property","decorators":[{"__symbolic":"call","expression":{"__symbolic":"reference","module":"@angular/core","name":"Input","line":20,"character":5}}]}],"layout":[{"__symbolic":"property","decorators":[{"__symbolic":"call","expression":{"__symbolic":"reference","module":"@angular/core","name":"Input","line":21,"character":5}}]}],"model":[{"__symbolic":"property","decorators":[{"__symbolic":"call","expression":{"__symbolic":"reference","module":"@angular/core","name":"Input","line":22,"character":5}}]}],"blur":[{"__symbolic":"property","decorators":[{"__symbolic":"call","expression":{"__symbolic":"reference","module":"@angular/core","name":"Output","line":24,"character":5}}]}],"change":[{"__symbolic":"property","decorators":[{"__symbolic":"call","expression":{"__symbolic":"reference","module":"@angular/core","name":"Output","line":25,"character":5}}]}],"customEvent":[{"__symbolic":"property","decorators":[{"__symbolic":"call","expression":{"__symbolic":"reference","module":"@angular/core","name":"Output","line":26,"character":5}}]}],"focus":[{"__symbolic":"property","decorators":[{"__symbolic":"call","expression":{"__symbolic":"reference","module":"@angular/core","name":"Output","line":27,"character":5}}]}],"kendoDatePicker":[{"__symbolic":"property","decorators":[{"__symbolic":"call","expression":{"__symbolic":"reference","module":"@angular/core","name":"ViewChild","line":29,"character":5},"arguments":["kendoDatePicker"]}]}],"__ctor__":[{"__symbolic":"constructor","parameters":[{"__symbolic":"reference","module":"@ng-dynamic-forms/core","name":"DynamicFormLayoutService","line":31,"character":41},{"__symbolic":"reference","module":"@ng-dynamic-forms/core","name":"DynamicFormValidationService","line":32,"character":45}]}]}},"DynamicKendoDropdownListComponent":{"__symbolic":"class","extends":{"__symbolic":"reference","name":"DynamicKendoTemplateableFormControlComponent"},"decorators":[{"__symbolic":"call","expression":{"__symbolic":"reference","module":"@angular/core","name":"Component","line":22,"character":1},"arguments":[{"selector":"dynamic-kendo-dropdownlist","changeDetection":{"__symbolic":"select","expression":{"__symbolic":"reference","module":"@angular/core","name":"ChangeDetectionStrategy","line":25,"character":21},"member":"OnPush"},"template":"<ng-container [formGroup]=\"group\">\r\n\r\n    <kendo-dropdownlist #kendoDropDownList\r\n                        [data]=\"model.options\"\r\n                        [delay]=\"model.getAdditional('delay', 500)\"\r\n                        [dynamicId]=\"bindId && model.id\"\r\n                        [filterable]=\"model.filterable\"\r\n                        [formControlName]=\"model.id\"\r\n                        [ignoreCase]=\"model.getAdditional('ignoreCase', true)\"\r\n                        [ngClass]=\"[getClass('element', 'control'), getClass('grid', 'control')]\"\r\n                        [popupSettings]=\"model.getAdditional('popupSettings', {})\"\r\n                        [tabIndex]=\"model.tabIndex\"\r\n                        [textField]=\"'label'\"\r\n                        [valueField]=\"'value'\"\r\n                        [valuePrimitive]=\"true\"\r\n                        (blur)=\"onBlur($event)\"\r\n                        (close)=\"onCustomEvent($event, 'close')\"\r\n                        (filterChange)=\"onCustomEvent($event, 'filterChange')\"\r\n                        (focus)=\"onFocus($event)\"\r\n                        (open)=\"onCustomEvent($event, 'open')\"\r\n                        (selectionChange)=\"onCustomEvent($event, 'selectionChange')\"\r\n                        (valueChange)=\"onChange($event)\"></kendo-dropdownlist>\r\n\r\n</ng-container>"}]}],"members":{"bindId":[{"__symbolic":"property","decorators":[{"__symbolic":"call","expression":{"__symbolic":"reference","module":"@angular/core","name":"Input","line":31,"character":5}}]}],"group":[{"__symbolic":"property","decorators":[{"__symbolic":"call","expression":{"__symbolic":"reference","module":"@angular/core","name":"Input","line":32,"character":5}}]}],"layout":[{"__symbolic":"property","decorators":[{"__symbolic":"call","expression":{"__symbolic":"reference","module":"@angular/core","name":"Input","line":33,"character":5}}]}],"model":[{"__symbolic":"property","decorators":[{"__symbolic":"call","expression":{"__symbolic":"reference","module":"@angular/core","name":"Input","line":34,"character":5}}]}],"templates":[{"__symbolic":"property","decorators":[{"__symbolic":"call","expression":{"__symbolic":"reference","module":"@angular/core","name":"Input","line":35,"character":5}}]}],"blur":[{"__symbolic":"property","decorators":[{"__symbolic":"call","expression":{"__symbolic":"reference","module":"@angular/core","name":"Output","line":37,"character":5}}]}],"change":[{"__symbolic":"property","decorators":[{"__symbolic":"call","expression":{"__symbolic":"reference","module":"@angular/core","name":"Output","line":38,"character":5}}]}],"customEvent":[{"__symbolic":"property","decorators":[{"__symbolic":"call","expression":{"__symbolic":"reference","module":"@angular/core","name":"Output","line":39,"character":5}}]}],"focus":[{"__symbolic":"property","decorators":[{"__symbolic":"call","expression":{"__symbolic":"reference","module":"@angular/core","name":"Output","line":40,"character":5}}]}],"kendoDropDownList":[{"__symbolic":"property","decorators":[{"__symbolic":"call","expression":{"__symbolic":"reference","module":"@angular/core","name":"ViewChild","line":42,"character":5},"arguments":["kendoDropDownList"]}]}],"__ctor__":[{"__symbolic":"constructor","parameters":[{"__symbolic":"reference","module":"@ng-dynamic-forms/core","name":"DynamicFormLayoutService","line":44,"character":41},{"__symbolic":"reference","module":"@ng-dynamic-forms/core","name":"DynamicFormValidationService","line":45,"character":45}]}]}},"DynamicKendoFormArrayComponent":{"__symbolic":"class","extends":{"__symbolic":"reference","module":"@ng-dynamic-forms/core","name":"DynamicFormArrayComponent","line":16,"character":52},"decorators":[{"__symbolic":"call","expression":{"__symbolic":"reference","module":"@angular/core","name":"Component","line":12,"character":1},"arguments":[{"selector":"dynamic-kendo-form-array","template":"<ng-container [formGroup]=\"group\">\r\n\r\n    <div [dynamicId]=\"bindId && model.id\"\r\n         [formArrayName]=\"model.id\"\r\n         [ngClass]=\"getClass('element', 'control')\">\r\n\r\n        <div *ngFor=\"let groupModel of model.groups; let idx = index\" role=\"group\"\r\n             [formGroupName]=\"idx\" [ngClass]=\"[getClass('element', 'group'), getClass('grid', 'group')]\">\r\n\r\n            <ng-container *ngTemplateOutlet=\"startTemplate?.templateRef; context: groupModel\"></ng-container>\r\n\r\n            <dynamic-kendo-form-control *ngFor=\"let _model of groupModel.group\"\r\n                                        [bindId]=\"false\"\r\n                                        [context]=\"groupModel\"\r\n                                        [group]=\"control.at(idx)\"\r\n                                        [hidden]=\"_model.hidden\"\r\n                                        [layout]=\"layout\"\r\n                                        [model]=\"_model\"\r\n                                        [templates]=\"templates\"\r\n                                        [ngClass]=\"[getClass('element', 'host', _model), getClass('grid', 'host', _model),\r\n                                                    getClass('element','children'), getClass('grid','children')]\"\r\n                                        (blur)=\"onBlur($event)\"\r\n                                        (change)=\"onChange($event)\"\r\n                                        (focus)=\"onFocus($event)\"\r\n                                        (kendoEvent)=\"onCustomEvent($event, null, true)\"></dynamic-kendo-form-control>\r\n\r\n            <ng-container *ngTemplateOutlet=\"endTemplate?.templateRef; context: groupModel\"></ng-container>\r\n\r\n        </div>\r\n\r\n    </div>\r\n\r\n</ng-container>"}]}],"members":{"bindId":[{"__symbolic":"property","decorators":[{"__symbolic":"call","expression":{"__symbolic":"reference","module":"@angular/core","name":"Input","line":18,"character":5}}]}],"group":[{"__symbolic":"property","decorators":[{"__symbolic":"call","expression":{"__symbolic":"reference","module":"@angular/core","name":"Input","line":19,"character":5}}]}],"layout":[{"__symbolic":"property","decorators":[{"__symbolic":"call","expression":{"__symbolic":"reference","module":"@angular/core","name":"Input","line":20,"character":5}}]}],"model":[{"__symbolic":"property","decorators":[{"__symbolic":"call","expression":{"__symbolic":"reference","module":"@angular/core","name":"Input","line":21,"character":5}}]}],"templates":[{"__symbolic":"property","decorators":[{"__symbolic":"call","expression":{"__symbolic":"reference","module":"@angular/core","name":"Input","line":22,"character":5}}]}],"blur":[{"__symbolic":"property","decorators":[{"__symbolic":"call","expression":{"__symbolic":"reference","module":"@angular/core","name":"Output","line":24,"character":5}}]}],"change":[{"__symbolic":"property","decorators":[{"__symbolic":"call","expression":{"__symbolic":"reference","module":"@angular/core","name":"Output","line":25,"character":5}}]}],"customEvent":[{"__symbolic":"property","decorators":[{"__symbolic":"call","expression":{"__symbolic":"reference","module":"@angular/core","name":"Output","line":26,"character":5}}]}],"focus":[{"__symbolic":"property","decorators":[{"__symbolic":"call","expression":{"__symbolic":"reference","module":"@angular/core","name":"Output","line":27,"character":5}}]}],"__ctor__":[{"__symbolic":"constructor","parameters":[{"__symbolic":"reference","module":"@ng-dynamic-forms/core","name":"DynamicFormLayoutService","line":29,"character":41},{"__symbolic":"reference","module":"@ng-dynamic-forms/core","name":"DynamicFormValidationService","line":30,"character":45}]}]}},"DynamicKendoFormGroupComponent":{"__symbolic":"class","extends":{"__symbolic":"reference","module":"@ng-dynamic-forms/core","name":"DynamicFormControlComponent","line":16,"character":52},"decorators":[{"__symbolic":"call","expression":{"__symbolic":"reference","module":"@angular/core","name":"Component","line":12,"character":1},"arguments":[{"selector":"dynamic-kendo-form-group","template":"<ng-container [formGroup]=\"group\">\r\n\r\n    <div role=\"group\"\r\n         [dynamicId]=\"bindId && model.id\"\r\n         [formGroupName]=\"model.id\"\r\n         [ngClass]=\"[getClass('element', 'control'), getClass('grid', 'control')]\">\r\n\r\n        <dynamic-kendo-form-control *ngFor=\"let _model of model.group\"\r\n                                    [group]=\"control\"\r\n                                    [hidden]=\"_model.hidden\"\r\n                                    [layout]=\"layout\"\r\n                                    [model]=\"_model\"\r\n                                    [templates]=\"templates\"\r\n                                    [ngClass]=\"[getClass('element', 'host', _model), getClass('grid', 'host', _model),\r\n                                                getClass('element','children'), getClass('grid','children')]\"\r\n                                    (blur)=\"onBlur($event)\"\r\n                                    (change)=\"onChange($event)\"\r\n                                    (focus)=\"onFocus($event)\"\r\n                                    (kendoEvent)=\"onCustomEvent($event, null, true)\"></dynamic-kendo-form-control>\r\n    </div>\r\n\r\n</ng-container>"}]}],"members":{"bindId":[{"__symbolic":"property","decorators":[{"__symbolic":"call","expression":{"__symbolic":"reference","module":"@angular/core","name":"Input","line":18,"character":5}}]}],"group":[{"__symbolic":"property","decorators":[{"__symbolic":"call","expression":{"__symbolic":"reference","module":"@angular/core","name":"Input","line":19,"character":5}}]}],"layout":[{"__symbolic":"property","decorators":[{"__symbolic":"call","expression":{"__symbolic":"reference","module":"@angular/core","name":"Input","line":20,"character":5}}]}],"model":[{"__symbolic":"property","decorators":[{"__symbolic":"call","expression":{"__symbolic":"reference","module":"@angular/core","name":"Input","line":21,"character":5}}]}],"templates":[{"__symbolic":"property","decorators":[{"__symbolic":"call","expression":{"__symbolic":"reference","module":"@angular/core","name":"Input","line":22,"character":5}}]}],"blur":[{"__symbolic":"property","decorators":[{"__symbolic":"call","expression":{"__symbolic":"reference","module":"@angular/core","name":"Output","line":24,"character":5}}]}],"change":[{"__symbolic":"property","decorators":[{"__symbolic":"call","expression":{"__symbolic":"reference","module":"@angular/core","name":"Output","line":25,"character":5}}]}],"customEvent":[{"__symbolic":"property","decorators":[{"__symbolic":"call","expression":{"__symbolic":"reference","module":"@angular/core","name":"Output","line":26,"character":5}}]}],"focus":[{"__symbolic":"property","decorators":[{"__symbolic":"call","expression":{"__symbolic":"reference","module":"@angular/core","name":"Output","line":27,"character":5}}]}],"__ctor__":[{"__symbolic":"constructor","parameters":[{"__symbolic":"reference","module":"@ng-dynamic-forms/core","name":"DynamicFormLayoutService","line":29,"character":41},{"__symbolic":"reference","module":"@ng-dynamic-forms/core","name":"DynamicFormValidationService","line":30,"character":45}]}]}},"DynamicKendoInputComponent":{"__symbolic":"class","extends":{"__symbolic":"reference","module":"@ng-dynamic-forms/core","name":"DynamicFormControlComponent","line":15,"character":48},"decorators":[{"__symbolic":"call","expression":{"__symbolic":"reference","module":"@angular/core","name":"Component","line":10,"character":1},"arguments":[{"selector":"dynamic-kendo-input","changeDetection":{"__symbolic":"select","expression":{"__symbolic":"reference","module":"@angular/core","name":"ChangeDetectionStrategy","line":13,"character":21},"member":"OnPush"},"template":"<label [formGroup]=\"group\" class=\"k-form-field\" [ngClass]=\"getClass('grid','control')\">\r\n\r\n    <span>\r\n\r\n        <span [innerHTML]=\"model.label\" [ngClass]=\"getClass('element','label')\"></span>\r\n\r\n        <span *ngIf=\"model.hint !== null\" class=\"k-field-info\" [innerHTML]=\"model.hint\"\r\n              [ngClass]=\"getClass('element','hint')\"></span>\r\n\r\n    </span>\r\n\r\n    <input class=\"k-textbox\"\r\n           [attr.accept]=\"model.accept\"\r\n           [attr.max]=\"model.max\"\r\n           [attr.min]=\"model.min\"\r\n           [attr.multiple]=\"model.multiple\"\r\n           [attr.step]=\"model.step\"\r\n           [autocomplete]=\"model.autoComplete\"\r\n           [autofocus]=\"model.autoFocus\"\r\n           [dynamicId]=\"bindId && model.id\"\r\n           [dynamicList]=\"model.listId\"\r\n           [formControlName]=\"model.id\"\r\n           [maxlength]=\"model.maxLength\"\r\n           [minlength]=\"model.minLength\"\r\n           [name]=\"model.name\"\r\n           [ngClass]=\"getClass('element','control')\"\r\n           [pattern]=\"model.pattern\"\r\n           [placeholder]=\"model.placeholder\"\r\n           [readonly]=\"model.readOnly\"\r\n           [required]=\"model.required\"\r\n           [spellcheck]=\"model.spellCheck\"\r\n           [tabindex]=\"model.tabIndex\"\r\n           [type]=\"model.inputType\"\r\n           (blur)=\"onBlur($event)\"\r\n           (change)=\"onChange($event)\"\r\n           (focus)=\"onFocus($event)\"/></label>\r\n"}]}],"members":{"bindId":[{"__symbolic":"property","decorators":[{"__symbolic":"call","expression":{"__symbolic":"reference","module":"@angular/core","name":"Input","line":17,"character":5}}]}],"group":[{"__symbolic":"property","decorators":[{"__symbolic":"call","expression":{"__symbolic":"reference","module":"@angular/core","name":"Input","line":18,"character":5}}]}],"layout":[{"__symbolic":"property","decorators":[{"__symbolic":"call","expression":{"__symbolic":"reference","module":"@angular/core","name":"Input","line":19,"character":5}}]}],"model":[{"__symbolic":"property","decorators":[{"__symbolic":"call","expression":{"__symbolic":"reference","module":"@angular/core","name":"Input","line":20,"character":5}}]}],"blur":[{"__symbolic":"property","decorators":[{"__symbolic":"call","expression":{"__symbolic":"reference","module":"@angular/core","name":"Output","line":22,"character":5}}]}],"change":[{"__symbolic":"property","decorators":[{"__symbolic":"call","expression":{"__symbolic":"reference","module":"@angular/core","name":"Output","line":23,"character":5}}]}],"focus":[{"__symbolic":"property","decorators":[{"__symbolic":"call","expression":{"__symbolic":"reference","module":"@angular/core","name":"Output","line":24,"character":5}}]}],"__ctor__":[{"__symbolic":"constructor","parameters":[{"__symbolic":"reference","module":"@ng-dynamic-forms/core","name":"DynamicFormLayoutService","line":26,"character":41},{"__symbolic":"reference","module":"@ng-dynamic-forms/core","name":"DynamicFormValidationService","line":27,"character":45}]}]}},"DynamicKendoMaskedTextBoxComponent":{"__symbolic":"class","extends":{"__symbolic":"reference","module":"@ng-dynamic-forms/core","name":"DynamicFormControlComponent","line":16,"character":56},"decorators":[{"__symbolic":"call","expression":{"__symbolic":"reference","module":"@angular/core","name":"Component","line":11,"character":1},"arguments":[{"selector":"dynamic-kendo-maskedtextbox","changeDetection":{"__symbolic":"select","expression":{"__symbolic":"reference","module":"@angular/core","name":"ChangeDetectionStrategy","line":14,"character":21},"member":"OnPush"},"template":"<ng-container [formGroup]=\"group\">\r\n\r\n    <kendo-maskedtextbox #kendoMaskedTextBox\r\n                         [dynamicId]=\"bindId && model.id\"\r\n                         [formControlName]=\"model.id\"\r\n                         [includeLiterals]=\"model.getAdditional('includeLiterals', false)\"\r\n                         [mask]=\"model.mask\"\r\n                         [maskValidation]=\"model.getAdditional('maskValidation', true)\"\r\n                         [ngClass]=\"[getClass('element', 'control'), getClass('grid', 'control')]\"\r\n                         [prompt]=\"model.getAdditional('prompt', '_')\"\r\n                         [promptPlaceholder]=\"model.getAdditional('promptPlaceholder', '')\"\r\n                         [tabIndex]=\"model.tabIndex\"\r\n                         (blur)=\"onBlur($event)\"\r\n                         (focus)=\"onFocus($event)\"\r\n                         (valueChange)=\"onChange($event)\"></kendo-maskedtextbox>\r\n\r\n</ng-container>"}]}],"members":{"bindId":[{"__symbolic":"property","decorators":[{"__symbolic":"call","expression":{"__symbolic":"reference","module":"@angular/core","name":"Input","line":18,"character":5}}]}],"group":[{"__symbolic":"property","decorators":[{"__symbolic":"call","expression":{"__symbolic":"reference","module":"@angular/core","name":"Input","line":19,"character":5}}]}],"layout":[{"__symbolic":"property","decorators":[{"__symbolic":"call","expression":{"__symbolic":"reference","module":"@angular/core","name":"Input","line":20,"character":5}}]}],"model":[{"__symbolic":"property","decorators":[{"__symbolic":"call","expression":{"__symbolic":"reference","module":"@angular/core","name":"Input","line":21,"character":5}}]}],"blur":[{"__symbolic":"property","decorators":[{"__symbolic":"call","expression":{"__symbolic":"reference","module":"@angular/core","name":"Output","line":23,"character":5}}]}],"change":[{"__symbolic":"property","decorators":[{"__symbolic":"call","expression":{"__symbolic":"reference","module":"@angular/core","name":"Output","line":24,"character":5}}]}],"focus":[{"__symbolic":"property","decorators":[{"__symbolic":"call","expression":{"__symbolic":"reference","module":"@angular/core","name":"Output","line":25,"character":5}}]}],"kendoMaskedTextBox":[{"__symbolic":"property","decorators":[{"__symbolic":"call","expression":{"__symbolic":"reference","module":"@angular/core","name":"ViewChild","line":27,"character":5},"arguments":["kendoMaskedTextBox"]}]}],"__ctor__":[{"__symbolic":"constructor","parameters":[{"__symbolic":"reference","module":"@ng-dynamic-forms/core","name":"DynamicFormLayoutService","line":29,"character":41},{"__symbolic":"reference","module":"@ng-dynamic-forms/core","name":"DynamicFormValidationService","line":30,"character":45}]}]}},"DynamicKendoMultiSelectComponent":{"__symbolic":"class","extends":{"__symbolic":"reference","name":"DynamicKendoTemplateableFormControlComponent"},"decorators":[{"__symbolic":"call","expression":{"__symbolic":"reference","module":"@angular/core","name":"Component","line":14,"character":1},"arguments":[{"selector":"dynamic-kendo-multiselect","changeDetection":{"__symbolic":"select","expression":{"__symbolic":"reference","module":"@angular/core","name":"ChangeDetectionStrategy","line":17,"character":21},"member":"OnPush"},"template":"<ng-container [formGroup]=\"group\">\r\n\r\n    <kendo-multiselect #kendoMultiSelect\r\n                       [autoClose]=\"model.getAdditional('autoClose', true)\"\r\n                       [clearButton]=\"model.getAdditional('clearButton', true)\"\r\n                       [data]=\"model.options\"\r\n                       [dynamicId]=\"bindId && model.id\"\r\n                       [formControlName]=\"model.id\"\r\n                       [ngClass]=\"[getClass('element', 'control'), getClass('grid', 'control')]\"\r\n                       [placeholder]=\"model.placeholder\"\r\n                       [popupSettings]=\"model.getAdditional('popupSettings', {})\"\r\n                       [tabIndex]=\"model.tabIndex\"\r\n                       [textField]=\"'label'\"\r\n                       [valueField]=\"'value'\"\r\n                       [valuePrimitive]=\"true\"\r\n                       (blur)=\"onBlur($event)\"\r\n                       (close)=\"onCustomEvent($event, 'close')\"\r\n                       (filterChange)=\"onCustomEvent($event, 'filterChange')\"\r\n                       (focus)=\"onFocus($event)\"\r\n                       (open)=\"onCustomEvent($event, 'open')\"\r\n                       (valueChange)=\"onChange($event)\"></kendo-multiselect>\r\n\r\n</ng-container>"}]}],"members":{"bindId":[{"__symbolic":"property","decorators":[{"__symbolic":"call","expression":{"__symbolic":"reference","module":"@angular/core","name":"Input","line":23,"character":5}}]}],"group":[{"__symbolic":"property","decorators":[{"__symbolic":"call","expression":{"__symbolic":"reference","module":"@angular/core","name":"Input","line":24,"character":5}}]}],"layout":[{"__symbolic":"property","decorators":[{"__symbolic":"call","expression":{"__symbolic":"reference","module":"@angular/core","name":"Input","line":25,"character":5}}]}],"model":[{"__symbolic":"property","decorators":[{"__symbolic":"call","expression":{"__symbolic":"reference","module":"@angular/core","name":"Input","line":26,"character":5}}]}],"templates":[{"__symbolic":"property","decorators":[{"__symbolic":"call","expression":{"__symbolic":"reference","module":"@angular/core","name":"Input","line":27,"character":5}}]}],"blur":[{"__symbolic":"property","decorators":[{"__symbolic":"call","expression":{"__symbolic":"reference","module":"@angular/core","name":"Output","line":29,"character":5}}]}],"change":[{"__symbolic":"property","decorators":[{"__symbolic":"call","expression":{"__symbolic":"reference","module":"@angular/core","name":"Output","line":30,"character":5}}]}],"customEvent":[{"__symbolic":"property","decorators":[{"__symbolic":"call","expression":{"__symbolic":"reference","module":"@angular/core","name":"Output","line":31,"character":5}}]}],"focus":[{"__symbolic":"property","decorators":[{"__symbolic":"call","expression":{"__symbolic":"reference","module":"@angular/core","name":"Output","line":32,"character":5}}]}],"kendoMultiSelect":[{"__symbolic":"property","decorators":[{"__symbolic":"call","expression":{"__symbolic":"reference","module":"@angular/core","name":"ViewChild","line":34,"character":5},"arguments":["kendoMultiSelect"]}]}],"__ctor__":[{"__symbolic":"constructor","parameters":[{"__symbolic":"reference","module":"@ng-dynamic-forms/core","name":"DynamicFormLayoutService","line":36,"character":41},{"__symbolic":"reference","module":"@ng-dynamic-forms/core","name":"DynamicFormValidationService","line":37,"character":45}]}]}},"DynamicKendoNumericTextBoxComponent":{"__symbolic":"class","extends":{"__symbolic":"reference","module":"@ng-dynamic-forms/core","name":"DynamicFormControlComponent","line":16,"character":57},"decorators":[{"__symbolic":"call","expression":{"__symbolic":"reference","module":"@angular/core","name":"Component","line":11,"character":1},"arguments":[{"selector":"dynamic-kendo-numerictextbox","changeDetection":{"__symbolic":"select","expression":{"__symbolic":"reference","module":"@angular/core","name":"ChangeDetectionStrategy","line":14,"character":21},"member":"OnPush"},"template":"<ng-container [formGroup]=\"group\">\r\n\r\n    <kendo-numerictextbox #kendoNumericTextBox\r\n                          [autoCorrect]=\"model.getAdditional('autoCorrect', false)\"\r\n                          [decimals]=\"model.getAdditional('decimals')\"\r\n                          [dynamicId]=\"bindId && model.id\"\r\n                          [format]=\"model.getAdditional('format', 'n0')\"\r\n                          [formControlName]=\"model.id\"\r\n                          [max]=\"model.max\"\r\n                          [min]=\"model.min\"\r\n                          [ngClass]=\"[getClass('element', 'control'), getClass('grid', 'control')]\"\r\n                          [placeholder]=\"model.placeholder\"\r\n                          [rangeValidation]=\"model.getAdditional('rangeValidation', true)\"\r\n                          [spinners]=\"model.getAdditional('spinners', true)\"\r\n                          [step]=\"model.step\"\r\n                          [tabIndex]=\"model.tabIndex\"\r\n                          (blur)=\"onBlur($event)\"\r\n                          (focus)=\"onFocus($event)\"\r\n                          (valueChange)=\"onChange($event)\"></kendo-numerictextbox>\r\n\r\n</ng-container>"}]}],"members":{"bindId":[{"__symbolic":"property","decorators":[{"__symbolic":"call","expression":{"__symbolic":"reference","module":"@angular/core","name":"Input","line":18,"character":5}}]}],"group":[{"__symbolic":"property","decorators":[{"__symbolic":"call","expression":{"__symbolic":"reference","module":"@angular/core","name":"Input","line":19,"character":5}}]}],"layout":[{"__symbolic":"property","decorators":[{"__symbolic":"call","expression":{"__symbolic":"reference","module":"@angular/core","name":"Input","line":20,"character":5}}]}],"model":[{"__symbolic":"property","decorators":[{"__symbolic":"call","expression":{"__symbolic":"reference","module":"@angular/core","name":"Input","line":21,"character":5}}]}],"blur":[{"__symbolic":"property","decorators":[{"__symbolic":"call","expression":{"__symbolic":"reference","module":"@angular/core","name":"Output","line":23,"character":5}}]}],"change":[{"__symbolic":"property","decorators":[{"__symbolic":"call","expression":{"__symbolic":"reference","module":"@angular/core","name":"Output","line":24,"character":5}}]}],"focus":[{"__symbolic":"property","decorators":[{"__symbolic":"call","expression":{"__symbolic":"reference","module":"@angular/core","name":"Output","line":25,"character":5}}]}],"kendoNumericTextBox":[{"__symbolic":"property","decorators":[{"__symbolic":"call","expression":{"__symbolic":"reference","module":"@angular/core","name":"ViewChild","line":27,"character":5},"arguments":["kendoNumericTextBox"]}]}],"__ctor__":[{"__symbolic":"constructor","parameters":[{"__symbolic":"reference","module":"@ng-dynamic-forms/core","name":"DynamicFormLayoutService","line":29,"character":41},{"__symbolic":"reference","module":"@ng-dynamic-forms/core","name":"DynamicFormValidationService","line":30,"character":45}]}]}},"DynamicKendoRadioGroupComponent":{"__symbolic":"class","extends":{"__symbolic":"reference","module":"@ng-dynamic-forms/core","name":"DynamicFormControlComponent","line":15,"character":53},"decorators":[{"__symbolic":"call","expression":{"__symbolic":"reference","module":"@angular/core","name":"Component","line":10,"character":1},"arguments":[{"selector":"dynamic-kendo-radio-group","changeDetection":{"__symbolic":"select","expression":{"__symbolic":"reference","module":"@angular/core","name":"ChangeDetectionStrategy","line":13,"character":21},"member":"OnPush"},"template":"<fieldset [formGroup]=\"group\" class=\"k-form-field\" role=\"radiogroup\"\r\n          [ngClass]=\"[getClass('element','control'), getClass('grid','control')]\">\r\n\r\n    <legend *ngIf=\"model.legend\" [innerHTML]=\"model.legend\"></legend>\r\n\r\n    <ng-container *ngFor=\"let option of model.options$ | async; let idx = index\">\r\n\r\n        <input type=\"radio\" class=\"k-radio\"\r\n               [formControlName]=\"model.id\"\r\n               [id]=\"'option' + idx + model.id\"\r\n               [name]=\"model.name\"\r\n               [ngClass]=\"[getClass('element','option'), getClass('grid','option')]\"\r\n               [value]=\"option.value\"\r\n               (blur)=\"onBlur($event)\"\r\n               (change)=\"onChange($event)\"\r\n               (focus)=\"onFocus($event)\"/>\r\n\r\n        <label class=\"k-radio-label\" [for]=\"'option' + idx + model.id\" [innerHTML]=\"option.label\"></label>\r\n\r\n    </ng-container>\r\n\r\n</fieldset>"}]}],"members":{"bindId":[{"__symbolic":"property","decorators":[{"__symbolic":"call","expression":{"__symbolic":"reference","module":"@angular/core","name":"Input","line":17,"character":5}}]}],"group":[{"__symbolic":"property","decorators":[{"__symbolic":"call","expression":{"__symbolic":"reference","module":"@angular/core","name":"Input","line":18,"character":5}}]}],"layout":[{"__symbolic":"property","decorators":[{"__symbolic":"call","expression":{"__symbolic":"reference","module":"@angular/core","name":"Input","line":19,"character":5}}]}],"model":[{"__symbolic":"property","decorators":[{"__symbolic":"call","expression":{"__symbolic":"reference","module":"@angular/core","name":"Input","line":20,"character":5}}]}],"blur":[{"__symbolic":"property","decorators":[{"__symbolic":"call","expression":{"__symbolic":"reference","module":"@angular/core","name":"Output","line":22,"character":5}}]}],"change":[{"__symbolic":"property","decorators":[{"__symbolic":"call","expression":{"__symbolic":"reference","module":"@angular/core","name":"Output","line":23,"character":5}}]}],"focus":[{"__symbolic":"property","decorators":[{"__symbolic":"call","expression":{"__symbolic":"reference","module":"@angular/core","name":"Output","line":24,"character":5}}]}],"__ctor__":[{"__symbolic":"constructor","parameters":[{"__symbolic":"reference","module":"@ng-dynamic-forms/core","name":"DynamicFormLayoutService","line":26,"character":41},{"__symbolic":"reference","module":"@ng-dynamic-forms/core","name":"DynamicFormValidationService","line":27,"character":45}]}]}},"DynamicKendoSliderComponent":{"__symbolic":"class","extends":{"__symbolic":"reference","module":"@ng-dynamic-forms/core","name":"DynamicFormControlComponent","line":16,"character":49},"decorators":[{"__symbolic":"call","expression":{"__symbolic":"reference","module":"@angular/core","name":"Component","line":11,"character":1},"arguments":[{"selector":"dynamic-kendo-slider","changeDetection":{"__symbolic":"select","expression":{"__symbolic":"reference","module":"@angular/core","name":"ChangeDetectionStrategy","line":14,"character":21},"member":"OnPush"},"template":"<ng-container [formGroup]=\"group\">\r\n\r\n    <kendo-slider #kendoSlider\r\n                  [dynamicId]=\"bindId && model.id\"\r\n                  [formControlName]=\"model.id\"\r\n                  [min]=\"model.min\"\r\n                  [max]=\"model.max\"\r\n                  [ngClass]=\"[getClass('element','control'), getClass('grid','control')]\"\r\n                  [showButtons]=\"model.getAdditional('showButtons', true)\"\r\n                  [smallStep]=\"model.step\"\r\n                  [tabIndex]=\"model.tabIndex\"\r\n                  [tickPlacement]=\"model.getAdditional('tickPlacement', 'both')\"\r\n                  [vertical]=\"model.vertical\"\r\n                  (valueChange)=\"onChange($event)\"></kendo-slider>\r\n\r\n</ng-container>"}]}],"members":{"bindId":[{"__symbolic":"property","decorators":[{"__symbolic":"call","expression":{"__symbolic":"reference","module":"@angular/core","name":"Input","line":18,"character":5}}]}],"group":[{"__symbolic":"property","decorators":[{"__symbolic":"call","expression":{"__symbolic":"reference","module":"@angular/core","name":"Input","line":19,"character":5}}]}],"layout":[{"__symbolic":"property","decorators":[{"__symbolic":"call","expression":{"__symbolic":"reference","module":"@angular/core","name":"Input","line":20,"character":5}}]}],"model":[{"__symbolic":"property","decorators":[{"__symbolic":"call","expression":{"__symbolic":"reference","module":"@angular/core","name":"Input","line":21,"character":5}}]}],"blur":[{"__symbolic":"property","decorators":[{"__symbolic":"call","expression":{"__symbolic":"reference","module":"@angular/core","name":"Output","line":23,"character":5}}]}],"change":[{"__symbolic":"property","decorators":[{"__symbolic":"call","expression":{"__symbolic":"reference","module":"@angular/core","name":"Output","line":24,"character":5}}]}],"focus":[{"__symbolic":"property","decorators":[{"__symbolic":"call","expression":{"__symbolic":"reference","module":"@angular/core","name":"Output","line":25,"character":5}}]}],"kendoSlider":[{"__symbolic":"property","decorators":[{"__symbolic":"call","expression":{"__symbolic":"reference","module":"@angular/core","name":"ViewChild","line":27,"character":5},"arguments":["kendoSlider"]}]}],"__ctor__":[{"__symbolic":"constructor","parameters":[{"__symbolic":"reference","module":"@ng-dynamic-forms/core","name":"DynamicFormLayoutService","line":29,"character":41},{"__symbolic":"reference","module":"@ng-dynamic-forms/core","name":"DynamicFormValidationService","line":30,"character":45}]}]}},"DynamicKendoSwitchComponent":{"__symbolic":"class","extends":{"__symbolic":"reference","module":"@ng-dynamic-forms/core","name":"DynamicFormControlComponent","line":16,"character":49},"decorators":[{"__symbolic":"call","expression":{"__symbolic":"reference","module":"@angular/core","name":"Component","line":11,"character":1},"arguments":[{"selector":"dynamic-kendo-switch","changeDetection":{"__symbolic":"select","expression":{"__symbolic":"reference","module":"@angular/core","name":"ChangeDetectionStrategy","line":14,"character":21},"member":"OnPush"},"template":"<ng-container [formGroup]=\"group\">\r\n\r\n    <kendo-switch #kendoSwitch\r\n                  [checked]=\"model.checked\"\r\n                  [dynamicId]=\"bindId && model.id\"\r\n                  [formControlName]=\"model.id\"\r\n                  [ngClass]=\"[getClass('element', 'control'), getClass('grid', 'control')]\"\r\n                  [offLabel]=\"model.offLabel\"\r\n                  [onLabel]=\"model.onLabel\"\r\n                  [tabIndex]=\"model.tabIndex\"\r\n                  (valueChange)=\"onChange($event)\"></kendo-switch>\r\n\r\n</ng-container>"}]}],"members":{"bindId":[{"__symbolic":"property","decorators":[{"__symbolic":"call","expression":{"__symbolic":"reference","module":"@angular/core","name":"Input","line":18,"character":5}}]}],"group":[{"__symbolic":"property","decorators":[{"__symbolic":"call","expression":{"__symbolic":"reference","module":"@angular/core","name":"Input","line":19,"character":5}}]}],"layout":[{"__symbolic":"property","decorators":[{"__symbolic":"call","expression":{"__symbolic":"reference","module":"@angular/core","name":"Input","line":20,"character":5}}]}],"model":[{"__symbolic":"property","decorators":[{"__symbolic":"call","expression":{"__symbolic":"reference","module":"@angular/core","name":"Input","line":21,"character":5}}]}],"blur":[{"__symbolic":"property","decorators":[{"__symbolic":"call","expression":{"__symbolic":"reference","module":"@angular/core","name":"Output","line":23,"character":5}}]}],"change":[{"__symbolic":"property","decorators":[{"__symbolic":"call","expression":{"__symbolic":"reference","module":"@angular/core","name":"Output","line":24,"character":5}}]}],"focus":[{"__symbolic":"property","decorators":[{"__symbolic":"call","expression":{"__symbolic":"reference","module":"@angular/core","name":"Output","line":25,"character":5}}]}],"kendoSwitch":[{"__symbolic":"property","decorators":[{"__symbolic":"call","expression":{"__symbolic":"reference","module":"@angular/core","name":"ViewChild","line":27,"character":5},"arguments":["kendoSwitch"]}]}],"__ctor__":[{"__symbolic":"constructor","parameters":[{"__symbolic":"reference","module":"@ng-dynamic-forms/core","name":"DynamicFormLayoutService","line":29,"character":41},{"__symbolic":"reference","module":"@ng-dynamic-forms/core","name":"DynamicFormValidationService","line":30,"character":45}]}]}},"DynamicKendoTextAreaComponent":{"__symbolic":"class","extends":{"__symbolic":"reference","module":"@ng-dynamic-forms/core","name":"DynamicFormControlComponent","line":15,"character":51},"decorators":[{"__symbolic":"call","expression":{"__symbolic":"reference","module":"@angular/core","name":"Component","line":10,"character":1},"arguments":[{"selector":"dynamic-kendo-textarea","changeDetection":{"__symbolic":"select","expression":{"__symbolic":"reference","module":"@angular/core","name":"ChangeDetectionStrategy","line":13,"character":21},"member":"OnPush"},"template":"<ng-container [formGroup]=\"group\">\r\n\r\n        <textarea class=\"k-textarea\"\r\n                  [cols]=\"model.cols\"\r\n                  [dynamicId]=\"bindId && model.id\"\r\n                  [formControlName]=\"model.id\"\r\n                  [maxlength]=\"model.maxLength\"\r\n                  [minlength]=\"model.minLength\"\r\n                  [name]=\"model.name\"\r\n                  [ngClass]=\"[getClass('element', 'control'), getClass('grid', 'control')]\"\r\n                  [placeholder]=\"model.placeholder\"\r\n                  [readonly]=\"model.readOnly\"\r\n                  [required]=\"model.required\"\r\n                  [rows]=\"model.rows\"\r\n                  [spellcheck]=\"model.spellCheck\"\r\n                  [tabindex]=\"model.tabIndex\"\r\n                  [wrap]=\"model.wrap\"\r\n                  (blur)=\"onBlur($event)\"\r\n                  (change)=\"onChange($event)\"\r\n                  (focus)=\"onFocus($event)\"></textarea>\r\n\r\n</ng-container>"}]}],"members":{"bindId":[{"__symbolic":"property","decorators":[{"__symbolic":"call","expression":{"__symbolic":"reference","module":"@angular/core","name":"Input","line":17,"character":5}}]}],"group":[{"__symbolic":"property","decorators":[{"__symbolic":"call","expression":{"__symbolic":"reference","module":"@angular/core","name":"Input","line":18,"character":5}}]}],"layout":[{"__symbolic":"property","decorators":[{"__symbolic":"call","expression":{"__symbolic":"reference","module":"@angular/core","name":"Input","line":19,"character":5}}]}],"model":[{"__symbolic":"property","decorators":[{"__symbolic":"call","expression":{"__symbolic":"reference","module":"@angular/core","name":"Input","line":20,"character":5}}]}],"blur":[{"__symbolic":"property","decorators":[{"__symbolic":"call","expression":{"__symbolic":"reference","module":"@angular/core","name":"Output","line":22,"character":5}}]}],"change":[{"__symbolic":"property","decorators":[{"__symbolic":"call","expression":{"__symbolic":"reference","module":"@angular/core","name":"Output","line":23,"character":5}}]}],"focus":[{"__symbolic":"property","decorators":[{"__symbolic":"call","expression":{"__symbolic":"reference","module":"@angular/core","name":"Output","line":24,"character":5}}]}],"__ctor__":[{"__symbolic":"constructor","parameters":[{"__symbolic":"reference","module":"@ng-dynamic-forms/core","name":"DynamicFormLayoutService","line":26,"character":41},{"__symbolic":"reference","module":"@ng-dynamic-forms/core","name":"DynamicFormValidationService","line":27,"character":45}]}]}},"DynamicKendoTimePickerComponent":{"__symbolic":"class","extends":{"__symbolic":"reference","module":"@ng-dynamic-forms/core","name":"DynamicFormControlComponent","line":17,"character":53},"decorators":[{"__symbolic":"call","expression":{"__symbolic":"reference","module":"@angular/core","name":"Component","line":12,"character":1},"arguments":[{"selector":"dynamic-kendo-timepicker","changeDetection":{"__symbolic":"select","expression":{"__symbolic":"reference","module":"@angular/core","name":"ChangeDetectionStrategy","line":15,"character":21},"member":"OnPush"},"template":"<ng-container [formGroup]=\"group\">\r\n\r\n    <kendo-timepicker #kendoTimePicker\r\n                      [cancelButton]=\"model.getAdditional('cancelButton', true)\"\r\n                      [dynamicId]=\"bindId && model.id\"\r\n                      [format]=\"model.format\"\r\n                      [formControlName]=\"model.id\"\r\n                      [formatPlaceholder]=\"model.getAdditional('formatPlaceholder', 'wide')\"\r\n                      [max]=\"model.max\"\r\n                      [min]=\"model.min\"\r\n                      [ngClass]=\"[getClass('element', 'control'), getClass('grid', 'control')]\"\r\n                      [nowButton]=\"model.getAdditional('nowButton', true)\"\r\n                      [popupSettings]=\"model.getAdditional('popupSettings', {})\"\r\n                      [rangeValidation]=\"model.getAdditional('rangeValidation', true)\"\r\n                      [steps]=\"model.getAdditional('steps', {})\"\r\n                      [tabindex]=\"model.tabIndex\"\r\n                      (blur)=\"onBlur($event)\"\r\n                      (close)=\"onCustomEvent($event, 'close')\"\r\n                      (focus)=\"onFocus($event)\"\r\n                      (open)=\"onCustomEvent($event, 'open')\"\r\n                      (valueChange)=\"onChange($event)\"></kendo-timepicker>\r\n\r\n</ng-container>"}]}],"members":{"bindId":[{"__symbolic":"property","decorators":[{"__symbolic":"call","expression":{"__symbolic":"reference","module":"@angular/core","name":"Input","line":19,"character":5}}]}],"group":[{"__symbolic":"property","decorators":[{"__symbolic":"call","expression":{"__symbolic":"reference","module":"@angular/core","name":"Input","line":20,"character":5}}]}],"layout":[{"__symbolic":"property","decorators":[{"__symbolic":"call","expression":{"__symbolic":"reference","module":"@angular/core","name":"Input","line":21,"character":5}}]}],"model":[{"__symbolic":"property","decorators":[{"__symbolic":"call","expression":{"__symbolic":"reference","module":"@angular/core","name":"Input","line":22,"character":5}}]}],"blur":[{"__symbolic":"property","decorators":[{"__symbolic":"call","expression":{"__symbolic":"reference","module":"@angular/core","name":"Output","line":24,"character":5}}]}],"change":[{"__symbolic":"property","decorators":[{"__symbolic":"call","expression":{"__symbolic":"reference","module":"@angular/core","name":"Output","line":25,"character":5}}]}],"customEvent":[{"__symbolic":"property","decorators":[{"__symbolic":"call","expression":{"__symbolic":"reference","module":"@angular/core","name":"Output","line":26,"character":5}}]}],"focus":[{"__symbolic":"property","decorators":[{"__symbolic":"call","expression":{"__symbolic":"reference","module":"@angular/core","name":"Output","line":27,"character":5}}]}],"kendoTimePicker":[{"__symbolic":"property","decorators":[{"__symbolic":"call","expression":{"__symbolic":"reference","module":"@angular/core","name":"ViewChild","line":29,"character":5},"arguments":["kendoTimePicker"]}]}],"__ctor__":[{"__symbolic":"constructor","parameters":[{"__symbolic":"reference","module":"@ng-dynamic-forms/core","name":"DynamicFormLayoutService","line":31,"character":41},{"__symbolic":"reference","module":"@ng-dynamic-forms/core","name":"DynamicFormValidationService","line":32,"character":45}]}]}},"DynamicKendoUploadComponent":{"__symbolic":"class","extends":{"__symbolic":"reference","name":"DynamicKendoTemplateableFormControlComponent"},"decorators":[{"__symbolic":"call","expression":{"__symbolic":"reference","module":"@angular/core","name":"Component","line":13,"character":1},"arguments":[{"selector":"dynamic-kendo-upload","changeDetection":{"__symbolic":"select","expression":{"__symbolic":"reference","module":"@angular/core","name":"ChangeDetectionStrategy","line":16,"character":21},"member":"OnPush"},"template":"<ng-container [formGroup]=\"group\">\r\n\r\n    <kendo-upload #kendoUpload\r\n                  [accept]=\"model.getAdditional('accept')\"\r\n                  [autoUpload]=\"model.autoUpload\"\r\n                  [batch]=\"model.getAdditional('batch', false)\"\r\n                  [dynamicId]=\"bindId && model.id\"\r\n                  [formControlName]=\"model.id\"\r\n                  [multiple]=\"model.multiple\"\r\n                  [ngClass]=\"[getClass('element', 'control'), getClass('grid', 'control')]\"\r\n                  [removeField]=\"model.getAdditional('removeField', 'fileNames')\"\r\n                  [removeMethod]=\"model.getAdditional('removeMethod', 'POST')\"\r\n                  [removeUrl]=\"model.removeUrl\"\r\n                  [responseType]=\"model.getAdditional('responseType', 'json')\"\r\n                  [saveField]=\"model.getAdditional('saveField', 'files')\"\r\n                  [saveMethod]=\"model.getAdditional('saveMethod', 'POST')\"\r\n                  [saveUrl]=\"model.url\"\r\n                  [showFileList]=\"model.showFileList\"\r\n                  [tabIndex]=\"model.tabIndex\"\r\n                  [withCredentials]=\"model.getAdditional('withCredentials', true)\"\r\n                  (blur)=\"onBlur($event)\"\r\n                  (cancel)=\"onCustomEvent($event, 'cancel')\"\r\n                  (change)=\"onChange($event)\"\r\n                  (clear)=\"onCustomEvent($event, 'clear')\"\r\n                  (complete)=\"onCustomEvent($event, 'complete')\"\r\n                  (error)=\"onCustomEvent($event, 'error')\"\r\n                  (focus)=\"onFocus($event)\"\r\n                  (remove)=\"onCustomEvent($event, 'remove')\"\r\n                  (select)=\"onCustomEvent($event, 'select')\"\r\n                  (success)=\"onCustomEvent($event, 'succes')\"\r\n                  (upload)=\"onCustomEvent($event, 'upload')\"\r\n                  (uploadProgress)=\"onCustomEvent($event, 'uploadProgress')\"\r\n                  (valueChange)=\"onChange($event)\"></kendo-upload>\r\n\r\n</ng-container>"}]}],"members":{"bindId":[{"__symbolic":"property","decorators":[{"__symbolic":"call","expression":{"__symbolic":"reference","module":"@angular/core","name":"Input","line":22,"character":5}}]}],"group":[{"__symbolic":"property","decorators":[{"__symbolic":"call","expression":{"__symbolic":"reference","module":"@angular/core","name":"Input","line":23,"character":5}}]}],"layout":[{"__symbolic":"property","decorators":[{"__symbolic":"call","expression":{"__symbolic":"reference","module":"@angular/core","name":"Input","line":24,"character":5}}]}],"model":[{"__symbolic":"property","decorators":[{"__symbolic":"call","expression":{"__symbolic":"reference","module":"@angular/core","name":"Input","line":25,"character":5}}]}],"templates":[{"__symbolic":"property","decorators":[{"__symbolic":"call","expression":{"__symbolic":"reference","module":"@angular/core","name":"Input","line":26,"character":5}}]}],"blur":[{"__symbolic":"property","decorators":[{"__symbolic":"call","expression":{"__symbolic":"reference","module":"@angular/core","name":"Output","line":28,"character":5}}]}],"change":[{"__symbolic":"property","decorators":[{"__symbolic":"call","expression":{"__symbolic":"reference","module":"@angular/core","name":"Output","line":29,"character":5}}]}],"customEvent":[{"__symbolic":"property","decorators":[{"__symbolic":"call","expression":{"__symbolic":"reference","module":"@angular/core","name":"Output","line":30,"character":5}}]}],"focus":[{"__symbolic":"property","decorators":[{"__symbolic":"call","expression":{"__symbolic":"reference","module":"@angular/core","name":"Output","line":31,"character":5}}]}],"kendoUpload":[{"__symbolic":"property","decorators":[{"__symbolic":"call","expression":{"__symbolic":"reference","module":"@angular/core","name":"ViewChild","line":33,"character":5},"arguments":["kendoUpload"]}]}],"__ctor__":[{"__symbolic":"constructor","parameters":[{"__symbolic":"reference","module":"@ng-dynamic-forms/core","name":"DynamicFormLayoutService","line":35,"character":41},{"__symbolic":"reference","module":"@ng-dynamic-forms/core","name":"DynamicFormValidationService","line":36,"character":45}]}]}},"DynamicKendoFormComponent":{"__symbolic":"class","extends":{"__symbolic":"reference","module":"@ng-dynamic-forms/core","name":"DynamicFormComponent","line":17,"character":47},"decorators":[{"__symbolic":"call","expression":{"__symbolic":"reference","module":"@angular/core","name":"Component","line":13,"character":1},"arguments":[{"selector":"dynamic-kendo-form","template":"<dynamic-kendo-form-control *ngFor=\"let model of formModel; trackBy: trackByFn\"\r\n                            [group]=\"formGroup\"\r\n                            [hidden]=\"model.hidden\"\r\n                            [layout]=\"formLayout\"\r\n                            [model]=\"model\"\r\n                            [ngClass]=\"[getClass(model,'element', 'host'), getClass(model,'grid', 'host')]\"\r\n                            [templates]=\"templates\"\r\n                            (blur)=\"onEvent($event, 'blur')\"\r\n                            (change)=\"onEvent($event, 'change')\"\r\n                            (focus)=\"onEvent($event, 'focus')\"\r\n                            (kendoEvent)=\"onEvent($event, 'custom')\"></dynamic-kendo-form-control>"}]}],"members":{"formGroup":[{"__symbolic":"property","decorators":[{"__symbolic":"call","expression":{"__symbolic":"reference","module":"@angular/core","name":"Input","line":19,"character":5},"arguments":["group"]}]}],"formModel":[{"__symbolic":"property","decorators":[{"__symbolic":"call","expression":{"__symbolic":"reference","module":"@angular/core","name":"Input","line":20,"character":5},"arguments":["model"]}]}],"formLayout":[{"__symbolic":"property","decorators":[{"__symbolic":"call","expression":{"__symbolic":"reference","module":"@angular/core","name":"Input","line":21,"character":5},"arguments":["layout"]}]}],"blur":[{"__symbolic":"property","decorators":[{"__symbolic":"call","expression":{"__symbolic":"reference","module":"@angular/core","name":"Output","line":23,"character":5}}]}],"change":[{"__symbolic":"property","decorators":[{"__symbolic":"call","expression":{"__symbolic":"reference","module":"@angular/core","name":"Output","line":24,"character":5}}]}],"focus":[{"__symbolic":"property","decorators":[{"__symbolic":"call","expression":{"__symbolic":"reference","module":"@angular/core","name":"Output","line":25,"character":5}}]}],"customEvent":[{"__symbolic":"property","decorators":[{"__symbolic":"call","expression":{"__symbolic":"reference","module":"@angular/core","name":"Output","line":26,"character":5},"arguments":["kendoEvent"]}]}],"templates":[{"__symbolic":"property","decorators":[{"__symbolic":"call","expression":{"__symbolic":"reference","module":"@angular/core","name":"ContentChildren","line":28,"character":5},"arguments":[{"__symbolic":"reference","module":"@ng-dynamic-forms/core","name":"DynamicTemplateDirective","line":28,"character":21}]}]}],"components":[{"__symbolic":"property","decorators":[{"__symbolic":"call","expression":{"__symbolic":"reference","module":"@angular/core","name":"ViewChildren","line":30,"character":5},"arguments":[{"__symbolic":"reference","name":"DynamicKendoFormControlContainerComponent"}]}]}],"__ctor__":[{"__symbolic":"constructor","parameters":[{"__symbolic":"reference","module":"@ng-dynamic-forms/core","name":"DynamicFormService","line":32,"character":39},{"__symbolic":"reference","module":"@ng-dynamic-forms/core","name":"DynamicFormLayoutService","line":32,"character":84}]}]}},"DynamicKendoFormControlContainerComponent":{"__symbolic":"class","extends":{"__symbolic":"reference","module":"@ng-dynamic-forms/core","name":"DynamicFormControlContainerComponent","line":66,"character":63},"decorators":[{"__symbolic":"call","expression":{"__symbolic":"reference","module":"@angular/core","name":"Component","line":62,"character":1},"arguments":[{"selector":"dynamic-kendo-form-control","template":"<div [formGroup]=\"group\" [ngClass]=\"[getClass('element', 'container'), getClass('grid', 'container')]\">\r\n\r\n    <label *ngIf=\"hasLabel\" [for]=\"model.id\" [ngClass]=\"[getClass('element', 'label'), getClass('grid', 'label')]\">\r\n\r\n        <span [innerHTML]=\"model.label\"></span>\r\n\r\n        <span *ngIf=\"hasHint\" class=\"k-field-info\" [innerHTML]=\"model.hint\" [ngClass]=\"getClass('element', 'hint')\"></span>\r\n\r\n    </label>\r\n\r\n    <ng-container *ngTemplateOutlet=\"startTemplate?.templateRef; context: model\"></ng-container>\r\n\r\n    <ng-container #componentViewContainer></ng-container>\r\n\r\n    <ul *ngIf=\"showErrorMessages\" [ngClass]=\"[getClass('element', 'errors'), getClass('grid', 'errors')]\">\r\n        <li *ngFor=\"let message of errorMessages\" class=\"k-field-info k-required\">{{ message }}</li>\r\n    </ul>\r\n\r\n    <ng-container *ngTemplateOutlet=\"endTemplate?.templateRef; context: model\"></ng-container>\r\n\r\n    <ng-content></ng-content>\r\n\r\n</div>"}]}],"members":{"contentTemplateList":[{"__symbolic":"property","decorators":[{"__symbolic":"call","expression":{"__symbolic":"reference","module":"@angular/core","name":"ContentChildren","line":68,"character":5},"arguments":[{"__symbolic":"reference","module":"@ng-dynamic-forms/core","name":"DynamicTemplateDirective","line":68,"character":21}]}]}],"inputTemplateList":[{"__symbolic":"property","decorators":[{"__symbolic":"call","expression":{"__symbolic":"reference","module":"@angular/core","name":"Input","line":69,"character":5},"arguments":["templates"]}]}],"bindId":[{"__symbolic":"property","decorators":[{"__symbolic":"call","expression":{"__symbolic":"reference","module":"@angular/core","name":"Input","line":71,"character":5}}]}],"context":[{"__symbolic":"property","decorators":[{"__symbolic":"call","expression":{"__symbolic":"reference","module":"@angular/core","name":"Input","line":72,"character":5}}]}],"group":[{"__symbolic":"property","decorators":[{"__symbolic":"call","expression":{"__symbolic":"reference","module":"@angular/core","name":"Input","line":73,"character":5}}]}],"layout":[{"__symbolic":"property","decorators":[{"__symbolic":"call","expression":{"__symbolic":"reference","module":"@angular/core","name":"Input","line":74,"character":5}}]}],"model":[{"__symbolic":"property","decorators":[{"__symbolic":"call","expression":{"__symbolic":"reference","module":"@angular/core","name":"Input","line":75,"character":5}}]}],"blur":[{"__symbolic":"property","decorators":[{"__symbolic":"call","expression":{"__symbolic":"reference","module":"@angular/core","name":"Output","line":77,"character":5}}]}],"change":[{"__symbolic":"property","decorators":[{"__symbolic":"call","expression":{"__symbolic":"reference","module":"@angular/core","name":"Output","line":78,"character":5}}]}],"focus":[{"__symbolic":"property","decorators":[{"__symbolic":"call","expression":{"__symbolic":"reference","module":"@angular/core","name":"Output","line":79,"character":5}}]}],"customEvent":[{"__symbolic":"property","decorators":[{"__symbolic":"call","expression":{"__symbolic":"reference","module":"@angular/core","name":"Output","line":80,"character":5},"arguments":["kendoEvent"]}]}],"componentViewContainerRef":[{"__symbolic":"property","decorators":[{"__symbolic":"call","expression":{"__symbolic":"reference","module":"@angular/core","name":"ViewChild","line":82,"character":5},"arguments":["componentViewContainer",{"read":{"__symbolic":"reference","module":"@angular/core","name":"ViewContainerRef","line":82,"character":48}}]}]}],"__ctor__":[{"__symbolic":"constructor","parameters":[{"__symbolic":"reference","module":"@angular/core","name":"ComponentFactoryResolver","line":84,"character":52},{"__symbolic":"reference","module":"@ng-dynamic-forms/core","name":"DynamicFormLayoutService","line":85,"character":41},{"__symbolic":"reference","module":"@ng-dynamic-forms/core","name":"DynamicFormValidationService","line":86,"character":45}]}]}},"kendoUIFormControlMapFn":{"__symbolic":"function"},"DynamicKendoTemplateableFormControlComponent":{"__symbolic":"class","extends":{"__symbolic":"reference","module":"@ng-dynamic-forms/core","name":"DynamicTemplateableFormControlComponent","line":3,"character":75},"members":{"mapTemplate":[{"__symbolic":"method"}]}},"KENDO_TEMPLATE_DIRECTIVES":{"__symbolic":"new","expression":{"__symbolic":"reference","name":"Map"},"arguments":[[["kendoAutoCompleteFooterTemplate","footerTemplate"],["kendoAutoCompleteHeaderTemplate","headerTemplate"],["kendoAutoCompleteItemTemplate","itemTemplate"],["kendoAutoCompleteNoDataTemplate","noDataTemplate"],["kendoCalendarCellTemplate","cellTemplate"],["kendoCalendarCenturyCellTemplate","centuryCellTemplate"],["kendoCalendarDecadeCellTemplate","decadeCellTemplate"],["kendoCalendarMonthCellTemplate","monthCellTemplate"],["kendoCalendarWeekNumberCellTemplate","weekNumberCellTemplate"],["kendoCalendarYearCellTemplate","yearCellTemplate"],["kendoDropDownListFooterTemplate","footerTemplate"],["kendoDropDownListHeaderTemplate","headerTemplate"],["kendoDropDownListItemTemplate","itemTemplate"],["kendoDropDownListNoDataTemplate","noDataTemplate"],["kendoDropDownListValueTemplate","valueTemplate"],["kendoMultiSelectListFooterTemplate","footerTemplate"],["kendoMultiSelectDropDownListHeaderTemplate","headerTemplate"],["kendoMultiSelectDropDownListItemTemplate","itemTemplate"],["kendoMultiSelectDropDownListNoDataTemplate","noDataTemplate"],["kendoMultiSelectDropDownListValueTemplate","valueTemplate"],["kendoUploadFileTemplate","fileTemplate"]]]},"DynamicFormsKendoUIModule":{"__symbolic":"class","decorators":[{"__symbolic":"call","expression":{"__symbolic":"reference","module":"@angular/core","name":"NgModule","line":30,"character":1},"arguments":[{"imports":[{"__symbolic":"reference","module":"@angular/common","name":"CommonModule","line":32,"character":8},{"__symbolic":"reference","module":"@angular/forms","name":"ReactiveFormsModule","line":33,"character":8},{"__symbolic":"reference","module":"@progress/kendo-angular-dateinputs","name":"DateInputsModule","line":34,"character":8},{"__symbolic":"reference","module":"@progress/kendo-angular-dropdowns","name":"DropDownsModule","line":35,"character":8},{"__symbolic":"reference","module":"@progress/kendo-angular-inputs","name":"InputsModule","line":36,"character":8},{"__symbolic":"reference","module":"@progress/kendo-angular-upload","name":"UploadModule","line":37,"character":8},{"__symbolic":"reference","module":"@ng-dynamic-forms/core","name":"DynamicFormsCoreModule","line":38,"character":8}],"declarations":[{"__symbolic":"reference","name":"DynamicKendoAutoCompleteComponent"},{"__symbolic":"reference","name":"DynamicKendoCalendarComponent"},{"__symbolic":"reference","name":"DynamicKendoCheckboxComponent"},{"__symbolic":"reference","name":"DynamicKendoCheckboxGroupComponent"},{"__symbolic":"reference","name":"DynamicKendoDateInputComponent"},{"__symbolic":"reference","name":"DynamicKendoDatePickerComponent"},{"__symbolic":"reference","name":"DynamicKendoDropdownListComponent"},{"__symbolic":"reference","name":"DynamicKendoFormArrayComponent"},{"__symbolic":"reference","name":"DynamicKendoFormGroupComponent"},{"__symbolic":"reference","name":"DynamicKendoInputComponent"},{"__symbolic":"reference","name":"DynamicKendoMaskedTextBoxComponent"},{"__symbolic":"reference","name":"DynamicKendoMultiSelectComponent"},{"__symbolic":"reference","name":"DynamicKendoNumericTextBoxComponent"},{"__symbolic":"reference","name":"DynamicKendoRadioGroupComponent"},{"__symbolic":"reference","name":"DynamicKendoSliderComponent"},{"__symbolic":"reference","name":"DynamicKendoSwitchComponent"},{"__symbolic":"reference","name":"DynamicKendoTextAreaComponent"},{"__symbolic":"reference","name":"DynamicKendoTimePickerComponent"},{"__symbolic":"reference","name":"DynamicKendoUploadComponent"},{"__symbolic":"reference","name":"DynamicKendoFormControlContainerComponent"},{"__symbolic":"reference","name":"DynamicKendoFormComponent"}],"entryComponents":[{"__symbolic":"reference","name":"DynamicKendoAutoCompleteComponent"},{"__symbolic":"reference","name":"DynamicKendoCalendarComponent"},{"__symbolic":"reference","name":"DynamicKendoCheckboxComponent"},{"__symbolic":"reference","name":"DynamicKendoCheckboxGroupComponent"},{"__symbolic":"reference","name":"DynamicKendoDateInputComponent"},{"__symbolic":"reference","name":"DynamicKendoDatePickerComponent"},{"__symbolic":"reference","name":"DynamicKendoDropdownListComponent"},{"__symbolic":"reference","name":"DynamicKendoFormArrayComponent"},{"__symbolic":"reference","name":"DynamicKendoFormGroupComponent"},{"__symbolic":"reference","name":"DynamicKendoInputComponent"},{"__symbolic":"reference","name":"DynamicKendoMaskedTextBoxComponent"},{"__symbolic":"reference","name":"DynamicKendoMultiSelectComponent"},{"__symbolic":"reference","name":"DynamicKendoNumericTextBoxComponent"},{"__symbolic":"reference","name":"DynamicKendoRadioGroupComponent"},{"__symbolic":"reference","name":"DynamicKendoSliderComponent"},{"__symbolic":"reference","name":"DynamicKendoSwitchComponent"},{"__symbolic":"reference","name":"DynamicKendoTextAreaComponent"},{"__symbolic":"reference","name":"DynamicKendoTimePickerComponent"},{"__symbolic":"reference","name":"DynamicKendoUploadComponent"}],"exports":[{"__symbolic":"reference","module":"@ng-dynamic-forms/core","name":"DynamicFormsCoreModule","line":85,"character":8},{"__symbolic":"reference","name":"DynamicKendoFormControlContainerComponent"},{"__symbolic":"reference","name":"DynamicKendoFormComponent"}]}]}],"members":{}}},"origins":{"DynamicKendoAutoCompleteComponent":"./src/autocomplete/dynamic-kendo-autocomplete.component","DynamicKendoCalendarComponent":"./src/calendar/dynamic-kendo-calendar.component","DynamicKendoCheckboxComponent":"./src/checkbox/dynamic-kendo-checkbox.component","DynamicKendoCheckboxGroupComponent":"./src/checkbox-group/dynamic-kendo-checkbox-group.component","DynamicKendoDateInputComponent":"./src/dateinput/dynamic-kendo-dateinput.component","DynamicKendoDatePickerComponent":"./src/datepicker/dynamic-kendo-datepicker.component","DynamicKendoDropdownListComponent":"./src/dropdownlist/dynamic-kendo-dropdownlist.component","DynamicKendoFormArrayComponent":"./src/form-array/dynamic-kendo-form-array.component","DynamicKendoFormGroupComponent":"./src/form-group/dynamic-kendo-form-group.component","DynamicKendoInputComponent":"./src/input/dynamic-kendo-input.component","DynamicKendoMaskedTextBoxComponent":"./src/masked-textbox/dynamic-kendo-maskedtextbox.component","DynamicKendoMultiSelectComponent":"./src/multiselect/dynamic-kendo-multiselect.component","DynamicKendoNumericTextBoxComponent":"./src/numeric-textbox/dynamic-kendo-numerictextbox.component","DynamicKendoRadioGroupComponent":"./src/radio-group/dynamic-kendo-radio-group.component","DynamicKendoSliderComponent":"./src/slider/dynamic-kendo-slider.component","DynamicKendoSwitchComponent":"./src/switch/dynamic-kendo-switch.component","DynamicKendoTextAreaComponent":"./src/textarea/dynamic-kendo-textarea.component","DynamicKendoTimePickerComponent":"./src/timepicker/dynamic-kendo-timepicker.component","DynamicKendoUploadComponent":"./src/upload/dynamic-kendo-upload.component","DynamicKendoFormComponent":"./src/dynamic-kendo-form.component","DynamicKendoFormControlContainerComponent":"./src/dynamic-kendo-form-control-container.component","kendoUIFormControlMapFn":"./src/dynamic-kendo-form-control-container.component","DynamicKendoTemplateableFormControlComponent":"./src/dynamic-kendo-templateable-form-control.component","KENDO_TEMPLATE_DIRECTIVES":"./src/dynamic-kendo-form.const","DynamicFormsKendoUIModule":"./src/dynamic-kendo-form-ui.module"},"importAs":"@ng-dynamic-forms/ui-kendo"}